README.md
setup.py
buildcage/__init__.py
buildcage/buildcage.py
buildcage/python.py
buildcage.egg-info/PKG-INFO
buildcage.egg-info/SOURCES.txt
buildcage.egg-info/dependency_links.txt
buildcage.egg-info/entry_points.txt
buildcage.egg-info/requires.txt
buildcage.egg-info/top_level.txt
buildcage/src/__init__.py
buildcage/src/bash.py
buildcage/src/boss.py
buildcage/src/lmp.py
buildcage/src/main.py
buildcage/src/molecule.py
buildcage/src/readjson.py
buildcage/src/stkcage.py
buildcage_old/__init__.py
buildcage_old/buildcage.py
buildcage_old/src/__init__.py
buildcage_old/src/bash.py
buildcage_old/src/lmp.py
buildcage_old/src/molecule.py
buildcage_old/src/readjson.py
buildcage_old/src/stkcage.py