Metadata-Version: 1.1
Name: buildcage
Version: 0.0.5
Summary: Python script to build cage optimimized by OPLS-AA
Home-page: UNKNOWN
Author: Kexin Zhang
Author-email: zhangkx2@shanghaitech.edu.cn
License: MIT
Keywords: computational chemistry,force fields,molecular dynamics,pore materials
Platform: UNKNOWN
Classifier: Programming Language :: Python :: 3
Classifier: Topic :: Scientific/Engineering
